{
  "opencollection": "1.0.0",
  "info": {
    "name": "Amazon DataSync REST API",
    "version": "2018-11-09"
  },
  "request": {
    "auth": {
      "type": "apikey",
      "key": "Authorization",
      "value": "{{Authorization}}",
      "placement": "header"
    }
  },
  "items": [
    {
      "info": {
        "name": "Default",
        "type": "folder"
      },
      "items": [
        {
          "info": {
            "name": "Amazon DataSync Create Task",
            "type": "http"
          },
          "http": {
            "method": "POST",
            "url": "https://datasync.{region}.amazonaws.com/",
            "body": {
              "type": "json",
              "data": "{}"
            }
          },
          "docs": "Configures a task, which defines where and how DataSync transfers your data."
        }
      ]
    },
    {
      "info": {
        "name": "#ListTasks",
        "type": "folder"
      },
      "items": [
        {
          "info": {
            "name": "Amazon DataSync List Tasks",
            "type": "http"
          },
          "http": {
            "method": "POST",
            "url": "https://datasync.{region}.amazonaws.com/#ListTasks",
            "body": {
              "type": "json",
              "data": "{}"
            }
          },
          "docs": "Returns a list of the DataSync tasks you created."
        }
      ]
    },
    {
      "info": {
        "name": "#DescribeTask",
        "type": "folder"
      },
      "items": [
        {
          "info": {
            "name": "Amazon DataSync Describe Task",
            "type": "http"
          },
          "http": {
            "method": "POST",
            "url": "https://datasync.{region}.amazonaws.com/#DescribeTask",
            "body": {
              "type": "json",
              "data": "{}"
            }
          },
          "docs": "Provides information about a DataSync transfer task."
        }
      ]
    },
    {
      "info": {
        "name": "#StartTaskExecution",
        "type": "folder"
      },
      "items": [
        {
          "info": {
            "name": "Amazon DataSync Start Task Execution",
            "type": "http"
          },
          "http": {
            "method": "POST",
            "url": "https://datasync.{region}.amazonaws.com/#StartTaskExecution",
            "body": {
              "type": "json",
              "data": "{}"
            }
          },
          "docs": "Starts an existing DataSync task. By starting a task, you tell DataSync to immediately begin transferring data."
        }
      ]
    },
    {
      "info": {
        "name": "#CreateLocationS3",
        "type": "folder"
      },
      "items": [
        {
          "info": {
            "name": "Amazon DataSync Create Location S3",
            "type": "http"
          },
          "http": {
            "method": "POST",
            "url": "https://datasync.{region}.amazonaws.com/#CreateLocationS3",
            "body": {
              "type": "json",
              "data": "{}"
            }
          },
          "docs": "Creates a transfer location for an Amazon S3 bucket."
        }
      ]
    },
    {
      "info": {
        "name": "#CreateAgent",
        "type": "folder"
      },
      "items": [
        {
          "info": {
            "name": "Amazon DataSync Create Agent",
            "type": "http"
          },
          "http": {
            "method": "POST",
            "url": "https://datasync.{region}.amazonaws.com/#CreateAgent",
            "body": {
              "type": "json",
              "data": "{}"
            }
          },
          "docs": "Activates an AWS DataSync agent that you've deployed in your storage environment."
        }
      ]
    }
  ],
  "bundled": true
}